<?xml version="1.0" encoding="utf-8"?>
<Dictionary>
	<Words>
		<Unrecognized>
			<Word>cb</Word>
			<Word>Multicolumn</Word>
			<Word>Subfield</Word>
			<Word>Endpoint</Word>
		</Unrecognized>
		<Recognized>
			<Word>deontic</Word>
			<Word>alethic</Word>
			<Word>contravariant</Word>
			<Word>supertype</Word>
			<Word>supertypes</Word>
			<Word>verbalizer</Word>
			<Word>Neumont</Word>
			<Word>Guids</Word>
			<Word>Colorizer</Word>
			<Word>Colorizable</Word>
			<Word>Arity</Word>
			<Word>Multi</Word>
			<Word>xml</Word>
			<Word>Irreflexive</Word>
			<Word>Antisymmetric</Word>
		</Recognized>
		<Deprecated/>
		<Inappropriate/>
	</Words>
	<Acronyms>
		<CasingExceptions>
			<Acronym>CJK</Acronym>
			<Acronym>ORM</Acronym>
			<Acronym>Pi</Acronym>
		</CasingExceptions>
	</Acronyms>
</Dictionary>
